ipag_core/__init__.py
ipag_core/cli.py
ipag_core/data.py
ipag_core/define.py
ipag_core/dev_tools.py
ipag_core/io/__init__.py
ipag_core/io/array.py
ipag_core/io/base.py
ipag_core/io/fits.py
ipag_core/ipag.py
ipag_core/log.py
ipag_core/metadata.py
ipag_core/metadata_model.py
ipag_core/path.py
ipag_core/processor.py
ipag_core/pydantic.py
ipag_core/types.py
ipag_core/yaml.py
ipag_core-0.1.16.dist-info/METADATA
ipag_core-0.1.16.dist-info/WHEEL
ipag_core-0.1.16.dist-info/RECORD
